bulk_sms_sender/__init__.py
bulk_sms_sender/sms_sender.py
bulk_sms_by_smslocal-0.1.dist-info/METADATA
bulk_sms_by_smslocal-0.1.dist-info/WHEEL
bulk_sms_by_smslocal-0.1.dist-info/top_level.txt
bulk_sms_by_smslocal-0.1.dist-info/RECORD
