Metadata-Version: 2.2
Name: bulk_sms_by_smslocal
Version: 0.1
Summary: A Python package to send bulk SMS using an external API.
Home-page: https://github.com/Smslocal001/bulk-sms
Author: Ariyan Khan
Author-email: ariyan@mycountrymobile.com
Classifier: Programming Language :: Python :: 3
Classifier: License :: OSI Approved :: MIT License
Classifier: Operating System :: OS Independent
Requires-Python: >=3.6
Requires-Dist: requests
Dynamic: author
Dynamic: author-email
Dynamic: classifier
Dynamic: description
Dynamic: description-content-type
Dynamic: home-page
Dynamic: requires-dist
Dynamic: requires-python
Dynamic: summary
